GetCovidData/src/__init__.py
GetCovidData/src/covidApi.py
GetCovidData-1.1.2.dist-info/LICENSE
GetCovidData-1.1.2.dist-info/METADATA
GetCovidData-1.1.2.dist-info/WHEEL
GetCovidData-1.1.2.dist-info/top_level.txt
GetCovidData-1.1.2.dist-info/RECORD
