Metadata-Version: 2.1
Name: GetCovidData
Version: 1.1.2
Summary: A simple python package to get Covid Stats just by using simple commands!
Author: Huzaifa Azhar
License-File: LICENSE
Requires-Dist: bs4
